{
  "parent": "minecraft:recipes/root",
  "criteria": {
    "has_gray_plank_fence_gate": {
      "conditions": {
        "items": [
          {
            "items": "desolatedpastels:gray_plank_fence_gate"
          }
        ]
      },
      "trigger": "minecraft:inventory_changed"
    },
    "has_gray_planks": {
      "conditions": {
        "items": [
          {
            "items": "desolatedpastels:gray_planks"
          }
        ]
      },
      "trigger": "minecraft:inventory_changed"
    },
    "has_stick": {
      "conditions": {
        "items": [
          {
            "items": "minecraft:stick"
          }
        ]
      },
      "trigger": "minecraft:inventory_changed"
    },
    "has_the_recipe": {
      "conditions": {
        "recipe": "desolatedpastels:gray_plank_fence_gate"
      },
      "trigger": "minecraft:recipe_unlocked"
    }
  },
  "requirements": [
    [
      "has_the_recipe",
      "has_stick",
      "has_gray_planks",
      "has_gray_plank_fence_gate"
    ]
  ],
  "rewards": {
    "recipes": [
      "desolatedpastels:gray_plank_fence_gate"
    ]
  }
}